gopythongo/__init__.py
gopythongo/main.py
gopythongo/vaultgetcert.py
gopythongo/vaultwrapper.py
gopythongo/assemblers/__init__.py
gopythongo/assemblers/certifybuild.py
gopythongo/assemblers/django.py
gopythongo/assemblers/help.py
gopythongo/assemblers/virtualenv.py
gopythongo/builders/__init__.py
gopythongo/builders/docker.py
gopythongo/builders/help.py
gopythongo/builders/noisolation.py
gopythongo/builders/pbuilder.py
gopythongo/initializers/__init__.py
gopythongo/initializers/docker_copy_docker.py
gopythongo/initializers/help.py
gopythongo/initializers/pbuilder_fpm_aptly.py
gopythongo/packers/__init__.py
gopythongo/packers/fpm.py
gopythongo/packers/help.py
gopythongo/packers/targz.py
gopythongo/shared/__init__.py
gopythongo/shared/aptly_args.py
gopythongo/shared/docker_args.py
gopythongo/stores/__init__.py
gopythongo/stores/aptly.py
gopythongo/stores/docker.py
gopythongo/stores/help.py
gopythongo/utils/__init__.py
gopythongo/utils/buildcontext.py
gopythongo/utils/debversion.py
gopythongo/utils/plugins.py
gopythongo/utils/targz.py
gopythongo/utils/template.py
gopythongo/versioners/__init__.py
gopythongo/versioners/aptly.py
gopythongo/versioners/bumpversion.py
gopythongo/versioners/help.py
gopythongo/versioners/pymodule.py
gopythongo/versioners/searchfile.py
gopythongo/versioners/static.py
gopythongo/versioners/parsers/__init__.py
gopythongo/versioners/parsers/debianparser.py
gopythongo/versioners/parsers/help.py
gopythongo/versioners/parsers/pep440parser.py
gopythongo/versioners/parsers/regexparser.py
gopythongo/versioners/parsers/semverparser.py
gopythongo-0.7.4.dev0.dist-info/METADATA
gopythongo-0.7.4.dev0.dist-info/RECORD
gopythongo-0.7.4.dev0.dist-info/WHEEL
gopythongo-0.7.4.dev0.dist-info/entry_points.txt
gopythongo-0.7.4.dev0.dist-info/top_level.txt
