Metadata-Version: 2.1
Name: gopythongo
Version: 0.7.4.dev0
Summary: Build shippable virtualenvs
Home-page: UNKNOWN
Author: Jonas Maurus (@jdelic)
Author-email: jonas@gopythongo.com
Maintainer: GoPythonGo.com
Maintainer-email: info@gopythongo.com
License: UNKNOWN
Platform: UNKNOWN
Classifier: Development Status :: 4 - Beta
Classifier: Intended Audience :: Developers
Classifier: Intended Audience :: System Administrators
Classifier: Environment :: Console
Classifier: Programming Language :: Python :: 3 :: Only
Classifier: License :: OSI Approved :: Mozilla Public License 2.0 (MPL 2.0)
Classifier: Operating System :: POSIX
Requires-Dist: Jinja2 (==2.10)
Requires-Dist: ConfigArgParse (==0.13.0)
Requires-Dist: Sphinx (==1.7.5)
Requires-Dist: sphinx-rtd-theme (==0.4.0)
Requires-Dist: colorama (==0.3.9)
Requires-Dist: semantic-version (==2.6.0)
Requires-Dist: packaging (==17.1)
Requires-Dist: typing (==3.6.4)
Requires-Dist: hvac (==0.6.0)
Requires-Dist: docker-py (==1.10.6)
Requires-Dist: dockerpty (==0.4.1)
Requires-Dist: pyopenssl (==18.0.0)
Requires-Dist: bumpversion (==0.5.3)
